prosemark/__init__.py
prosemark/_version.py
prosemark/exceptions.py
prosemark/py.typed
prosemark/adapters/__init__.py
prosemark/adapters/binder_repo_fs.py
prosemark/adapters/binder_scaffold.py
prosemark/adapters/clock_system.py
prosemark/adapters/console_pretty.py
prosemark/adapters/daily_repo_fs.py
prosemark/adapters/editor_launcher_system.py
prosemark/adapters/fake_clock.py
prosemark/adapters/fake_config.py
prosemark/adapters/fake_console.py
prosemark/adapters/fake_id_generator.py
prosemark/adapters/fake_logger.py
prosemark/adapters/fake_node_repo.py
prosemark/adapters/fake_storage.py
prosemark/adapters/frontmatter_codec.py
prosemark/adapters/frontmatter_codec.py.backup
prosemark/adapters/id_generator.py
prosemark/adapters/id_generator_uuid7.py
prosemark/adapters/logger_stdout.py
prosemark/adapters/markdown_binder_parser.py
prosemark/adapters/markdown_binder_parser.py.backup
prosemark/adapters/node_repo_fs.py
prosemark/app/__init__.py
prosemark/app/add_node.py
prosemark/app/audit_project.py
prosemark/app/init_project.py
prosemark/app/materialize_all_placeholders.py
prosemark/app/materialize_node.py
prosemark/app/move_node.py
prosemark/app/remove_node.py
prosemark/app/use_cases.py
prosemark/app/compile/__init__.py
prosemark/app/compile/use_cases.py
prosemark/cli/__init__.py
prosemark/cli/add.py
prosemark/cli/audit.py
prosemark/cli/compile.py
prosemark/cli/edit.py
prosemark/cli/init.py
prosemark/cli/main.py
prosemark/cli/materialize.py
prosemark/cli/move.py
prosemark/cli/remove.py
prosemark/cli/structure.py
prosemark/cli/write.py
prosemark/domain/__init__.py
prosemark/domain/batch_materialize_result.py
prosemark/domain/binder.py
prosemark/domain/entities.py
prosemark/domain/materialize_failure.py
prosemark/domain/materialize_result.py
prosemark/domain/models.py
prosemark/domain/parser_result.py
prosemark/domain/placeholder_summary.py
prosemark/domain/policies.py
prosemark/domain/position_anchor.py
prosemark/domain/preserved_text.py
prosemark-0.4.1.dist-info/METADATA
prosemark-0.4.1.dist-info/WHEEL
prosemark-0.4.1.dist-info/entry_points.txt
prosemark-0.4.1.dist-info/licenses/LICENSE.md
prosemark-0.4.1.dist-info/RECORD
