Metadata-Version: 2.4
Name: prosemark
Version: 0.4.1
Summary: A command-line tool for planning, organizing, and writing stories using a hierarchical document structure
Author-email: David Eyk <david@worldsenoughstudios.com>
License-Expression: MIT
License-File: LICENSE.md
Classifier: Development Status :: 3 - Alpha
Classifier: Intended Audience :: Developers
Classifier: License :: OSI Approved :: MIT License
Classifier: Operating System :: OS Independent
Classifier: Programming Language :: Python :: 3
Classifier: Topic :: Artistic Software
Classifier: Topic :: Office/Business
Classifier: Topic :: Software Development :: Libraries
Classifier: Topic :: Text Editors
Classifier: Topic :: Text Editors :: Integrated Development Environments (IDE)
Classifier: Topic :: Text Editors :: Text Processing
Classifier: Topic :: Text Processing
Classifier: Topic :: Text Processing :: Markup :: Markdown
Requires-Python: >=3.13
Requires-Dist: click-extra[pygments]>=4.15.0
Requires-Dist: click>=8.1.8
Requires-Dist: polyfactory>=2.21.0
Requires-Dist: prompt-toolkit>=3.0.51
Requires-Dist: pydantic>=2.11.4
Requires-Dist: pyyaml>=6.0.2
Requires-Dist: textual>=0.63.0
Requires-Dist: typer>=0.12.0
Requires-Dist: types-psutil>=7.0.0.20250822
Requires-Dist: uuid-extension>=0.2.0
